{
    "version": "5.11.0.v202603030810",
    "created": "2026-03-18 22:52",
    "nodestats": {
        "nodes": [
        ],
        "metaNodes": {
        },
        "wrappedNodes": {
        },
        "createdVia": {
        }
    },
    "uptime": 100157,
    "workflowsOpened": 1,
    "remoteWorkflowsOpened": 0,
    "workflowsCreated": 0,
    "remoteWorkflowsCreated": 0,
    "columnarStorageWorkflowsOpened": 0,
    "workflowsImported": 0,
    "workflowsExported": 0,
    "webUIPerspectiveSwitches": 0,
    "javaUIPerspectiveSwitches": 0,
    "lastUsedPerspective": "none",
    "launches": 1,
    "lastApplicationID": "org.knime.product.KNIME_APPLICATION",
    "timeSinceLastStart": 100157,
    "crashes": 0,
    "properlyShutDown": true
}